{
  "runs": [
    [
      {
        "store": "Dianella",
        "timestamp": "2026-05-12T20:02:54.229325+08:00",
        "available": false,
        "products": [
          {
            "name": "Osem Bamba Peanut Snack KB | 25g",
            "price": "$2.00",
            "available": false
          },
          {
            "name": "Osem Bamba Peanut Snack | 100g",
            "price": "n/a",
            "available": false
          }
        ]
      },
      {
        "store": "Mirrabooka",
        "timestamp": "2026-05-12T20:03:15.353233+08:00",
        "available": true,
        "products": [
          {
            "name": "Osem Bamba Peanut Snack KB | 25g",
            "price": "$2.00",
            "available": true
          },
          {
            "name": "Osem Bamba Peanut Snack | 100g",
            "price": "n/a",
            "available": false
          }
        ]
      }
    ],
    [
      {
        "store": "Dianella",
        "timestamp": "2026-05-13T08:08:22.086945+08:00",
        "available": false,
        "products": [
          {
            "name": "Osem Bamba Peanut Snack KB | 25g",
            "price": "$2.00",
            "available": false
          },
          {
            "name": "Osem Bamba Peanut Snack | 100g",
            "price": "n/a",
            "available": false
          }
        ]
      },
      {
        "store": "Mirrabooka",
        "timestamp": "2026-05-13T08:08:45.084859+08:00",
        "available": true,
        "products": [
          {
            "name": "Osem Bamba Peanut Snack KB | 25g",
            "price": "$2.00",
            "available": true
          },
          {
            "name": "Osem Bamba Peanut Snack | 100g",
            "price": "n/a",
            "available": false
          }
        ]
      }
    ],
    [
      {
        "store": "Dianella",
        "timestamp": "2026-05-13T12:54:08.062525+08:00",
        "available": false,
        "products": [
          {
            "name": "Osem Bamba Peanut Snack KB | 25g",
            "price": "$2.00",
            "available": false
          },
          {
            "name": "Osem Bamba Peanut Snack | 100g",
            "price": "n/a",
            "available": false
          }
        ]
      },
      {
        "store": "Mirrabooka",
        "timestamp": "2026-05-13T12:54:26.954348+08:00",
        "available": true,
        "products": [
          {
            "name": "Osem Bamba Peanut Snack KB | 25g",
            "price": "$2.00",
            "available": true
          },
          {
            "name": "Osem Bamba Peanut Snack | 100g",
            "price": "n/a",
            "available": false
          }
        ]
      }
    ],
    [
      {
        "store": "Dianella",
        "timestamp": "2026-05-13T15:55:47.531224+08:00",
        "available": false,
        "products": [
          {
            "name": "Osem Bamba Peanut Snack KB | 25g",
            "price": "$2.00",
            "available": false
          },
          {
            "name": "Osem Bamba Peanut Snack | 100g",
            "price": "n/a",
            "available": false
          }
        ]
      },
      {
        "store": "Mirrabooka",
        "timestamp": "2026-05-13T15:56:09.571383+08:00",
        "available": true,
        "products": [
          {
            "name": "Osem Bamba Peanut Snack KB | 25g",
            "price": "$2.00",
            "available": true
          },
          {
            "name": "Osem Bamba Peanut Snack | 100g",
            "price": "n/a",
            "available": false
          }
        ]
      }
    ],
    [
      {
        "store": "Dianella",
        "timestamp": "2026-05-13T18:37:32.405395+08:00",
        "available": false,
        "products": [
          {
            "name": "Osem Bamba Peanut Snack KB | 25g",
            "price": "$2.00",
            "available": false
          },
          {
            "name": "Osem Bamba Peanut Snack | 100g",
            "price": "n/a",
            "available": false
          }
        ]
      },
      {
        "store": "Mirrabooka",
        "timestamp": "2026-05-13T18:37:53.031686+08:00",
        "available": true,
        "products": [
          {
            "name": "Osem Bamba Peanut Snack KB | 25g",
            "price": "$2.00",
            "available": true
          },
          {
            "name": "Osem Bamba Peanut Snack | 100g",
            "price": "n/a",
            "available": false
          }
        ]
      }
    ],
    [
      {
        "store": "Dianella",
        "timestamp": "2026-05-13T21:22:38.312760+08:00",
        "available": false,
        "products": [
          {
            "name": "Osem Bamba Peanut Snack KB | 25g",
            "price": "$2.00",
            "available": false
          },
          {
            "name": "Osem Bamba Peanut Snack | 100g",
            "price": "n/a",
            "available": false
          }
        ]
      },
      {
        "store": "Mirrabooka",
        "timestamp": "2026-05-13T21:22:57.262941+08:00",
        "available": true,
        "products": [
          {
            "name": "Osem Bamba Peanut Snack KB | 25g",
            "price": "$2.00",
            "available": true
          },
          {
            "name": "Osem Bamba Peanut Snack | 100g",
            "price": "n/a",
            "available": false
          }
        ]
      }
    ],
    [
      {
        "store": "Dianella",
        "timestamp": "2026-05-14T07:13:07.225203+08:00",
        "available": true,
        "products": [
          {
            "name": "Osem Bamba Peanut Snack KB | 25g",
            "price": "$2.00",
            "available": true
          },
          {
            "name": "Osem Bamba Peanut Snack | 100g",
            "price": "n/a",
            "available": false
          }
        ]
      },
      {
        "store": "Mirrabooka",
        "timestamp": "2026-05-14T07:13:28.910922+08:00",
        "available": true,
        "products": [
          {
            "name": "Osem Bamba Peanut Snack KB | 25g",
            "price": "$2.00",
            "available": true
          },
          {
            "name": "Osem Bamba Peanut Snack | 100g",
            "price": "n/a",
            "available": false
          }
        ]
      }
    ],
    [
      {
        "store": "Dianella",
        "timestamp": "2026-05-14T12:04:58.834482+08:00",
        "available": true,
        "products": [
          {
            "name": "Osem Bamba Peanut Snack KB | 25g",
            "price": "$2.00",
            "available": true
          },
          {
            "name": "Osem Bamba Peanut Snack | 100g",
            "price": "n/a",
            "available": false
          }
        ]
      },
      {
        "store": "Mirrabooka",
        "timestamp": "2026-05-14T12:05:21.275550+08:00",
        "available": true,
        "products": [
          {
            "name": "Osem Bamba Peanut Snack KB | 25g",
            "price": "$2.00",
            "available": true
          },
          {
            "name": "Osem Bamba Peanut Snack | 100g",
            "price": "n/a",
            "available": false
          }
        ]
      }
    ],
    [
      {
        "store": "Dianella",
        "timestamp": "2026-05-14T15:49:15.609456+08:00",
        "available": true,
        "products": [
          {
            "name": "Osem Bamba Peanut Snack KB | 25g",
            "price": "$2.00",
            "available": true
          },
          {
            "name": "Osem Bamba Peanut Snack | 100g",
            "price": "n/a",
            "available": false
          }
        ]
      },
      {
        "store": "Mirrabooka",
        "timestamp": "2026-05-14T15:49:53.907442+08:00",
        "available": true,
        "products": [
          {
            "name": "Osem Bamba Peanut Snack KB | 25g",
            "price": "$2.00",
            "available": true
          },
          {
            "name": "Osem Bamba Peanut Snack | 100g",
            "price": "n/a",
            "available": false
          }
        ]
      }
    ],
    [
      {
        "store": "Dianella",
        "timestamp": "2026-05-14T18:27:39.224447+08:00",
        "available": true,
        "products": [
          {
            "name": "Osem Bamba Peanut Snack KB | 25g",
            "price": "$2.00",
            "available": true
          },
          {
            "name": "Osem Bamba Peanut Snack | 100g",
            "price": "n/a",
            "available": false
          }
        ]
      },
      {
        "store": "Mirrabooka",
        "timestamp": "2026-05-14T18:27:58.872045+08:00",
        "available": true,
        "products": [
          {
            "name": "Osem Bamba Peanut Snack KB | 25g",
            "price": "$2.00",
            "available": true
          },
          {
            "name": "Osem Bamba Peanut Snack | 100g",
            "price": "n/a",
            "available": false
          }
        ]
      }
    ],
    [
      {
        "store": "Dianella",
        "timestamp": "2026-05-14T20:58:29.367377+08:00",
        "available": true,
        "products": [
          {
            "name": "Osem Bamba Peanut Snack KB | 25g",
            "price": "$2.00",
            "available": true
          },
          {
            "name": "Osem Bamba Peanut Snack | 100g",
            "price": "n/a",
            "available": false
          }
        ]
      },
      {
        "store": "Mirrabooka",
        "timestamp": "2026-05-14T20:58:51.380970+08:00",
        "available": true,
        "products": [
          {
            "name": "Osem Bamba Peanut Snack KB | 25g",
            "price": "$2.00",
            "available": true
          },
          {
            "name": "Osem Bamba Peanut Snack | 100g",
            "price": "n/a",
            "available": false
          }
        ]
      }
    ],
    [
      {
        "store": "Dianella",
        "timestamp": "2026-05-15T08:03:41.490992+08:00",
        "available": true,
        "products": [
          {
            "name": "Osem Bamba Peanut Snack KB | 25g",
            "price": "$2.00",
            "available": true
          },
          {
            "name": "Osem Bamba Peanut Snack | 100g",
            "price": "n/a",
            "available": false
          }
        ]
      },
      {
        "store": "Mirrabooka",
        "timestamp": "2026-05-15T08:04:03.285020+08:00",
        "available": true,
        "products": [
          {
            "name": "Osem Bamba Peanut Snack KB | 25g",
            "price": "$2.00",
            "available": true
          },
          {
            "name": "Osem Bamba Peanut Snack | 100g",
            "price": "n/a",
            "available": false
          }
        ]
      }
    ],
    [
      {
        "store": "Dianella",
        "timestamp": "2026-05-15T12:56:36.787723+08:00",
        "available": true,
        "products": [
          {
            "name": "Osem Bamba Peanut Snack KB | 25g",
            "price": "$2.00",
            "available": true
          },
          {
            "name": "Osem Bamba Peanut Snack | 100g",
            "price": "n/a",
            "available": false
          }
        ]
      },
      {
        "store": "Mirrabooka",
        "timestamp": "2026-05-15T12:56:57.152767+08:00",
        "available": true,
        "products": [
          {
            "name": "Osem Bamba Peanut Snack KB | 25g",
            "price": "$2.00",
            "available": true
          },
          {
            "name": "Osem Bamba Peanut Snack | 100g",
            "price": "n/a",
            "available": false
          }
        ]
      }
    ],
    [
      {
        "store": "Dianella",
        "timestamp": "2026-05-15T19:26:17.370345+08:00",
        "available": true,
        "products": [
          {
            "name": "Osem Bamba Peanut Snack KB | 25g",
            "price": "$2.00",
            "available": true
          },
          {
            "name": "Osem Bamba Peanut Snack | 100g",
            "price": "n/a",
            "available": false
          }
        ]
      },
      {
        "store": "Mirrabooka",
        "timestamp": "2026-05-15T19:26:38.393118+08:00",
        "available": true,
        "products": [
          {
            "name": "Osem Bamba Peanut Snack KB | 25g",
            "price": "$2.00",
            "available": true
          },
          {
            "name": "Osem Bamba Peanut Snack | 100g",
            "price": "n/a",
            "available": false
          }
        ]
      }
    ],
    [
      {
        "store": "Dianella",
        "timestamp": "2026-05-15T22:26:44.040596+08:00",
        "available": true,
        "products": [
          {
            "name": "Osem Bamba Peanut Snack KB | 25g",
            "price": "$2.00",
            "available": true
          },
          {
            "name": "Osem Bamba Peanut Snack | 100g",
            "price": "n/a",
            "available": false
          }
        ]
      },
      {
        "store": "Mirrabooka",
        "timestamp": "2026-05-15T22:27:07.147937+08:00",
        "available": true,
        "products": [
          {
            "name": "Osem Bamba Peanut Snack KB | 25g",
            "price": "$2.00",
            "available": true
          },
          {
            "name": "Osem Bamba Peanut Snack | 100g",
            "price": "n/a",
            "available": false
          }
        ]
      }
    ],
    [
      {
        "store": "Dianella",
        "timestamp": "2026-05-16T08:00:09.632338+08:00",
        "available": true,
        "products": [
          {
            "name": "Osem Bamba Peanut Snack KB | 25g",
            "price": "$2.00",
            "available": true
          },
          {
            "name": "Osem Bamba Peanut Snack | 100g",
            "price": "n/a",
            "available": false
          }
        ]
      },
      {
        "store": "Mirrabooka",
        "timestamp": "2026-05-16T08:00:29.614583+08:00",
        "available": true,
        "products": [
          {
            "name": "Osem Bamba Peanut Snack KB | 25g",
            "price": "$2.00",
            "available": true
          },
          {
            "name": "Osem Bamba Peanut Snack | 100g",
            "price": "n/a",
            "available": false
          }
        ]
      }
    ],
    [
      {
        "store": "Dianella",
        "timestamp": "2026-05-16T11:56:20.592628+08:00",
        "available": true,
        "products": [
          {
            "name": "Osem Bamba Peanut Snack KB | 25g",
            "price": "$2.00",
            "available": true
          },
          {
            "name": "Osem Bamba Peanut Snack | 100g",
            "price": "n/a",
            "available": false
          }
        ]
      },
      {
        "store": "Mirrabooka",
        "timestamp": "2026-05-16T11:56:43.693292+08:00",
        "available": true,
        "products": [
          {
            "name": "Osem Bamba Peanut Snack KB | 25g",
            "price": "$2.00",
            "available": true
          },
          {
            "name": "Osem Bamba Peanut Snack | 100g",
            "price": "n/a",
            "available": false
          }
        ]
      }
    ],
    [
      {
        "store": "Dianella",
        "timestamp": "2026-05-16T14:29:10.598687+08:00",
        "available": true,
        "products": [
          {
            "name": "Osem Bamba Peanut Snack KB | 25g",
            "price": "$2.00",
            "available": true
          },
          {
            "name": "Osem Bamba Peanut Snack | 100g",
            "price": "n/a",
            "available": false
          }
        ]
      },
      {
        "store": "Mirrabooka",
        "timestamp": "2026-05-16T14:29:32.683508+08:00",
        "available": true,
        "products": [
          {
            "name": "Osem Bamba Peanut Snack KB | 25g",
            "price": "$2.00",
            "available": true
          },
          {
            "name": "Osem Bamba Peanut Snack | 100g",
            "price": "n/a",
            "available": false
          }
        ]
      }
    ],
    [
      {
        "store": "Dianella",
        "timestamp": "2026-05-16T16:53:42.509211+08:00",
        "available": true,
        "products": [
          {
            "name": "Osem Bamba Peanut Snack KB | 25g",
            "price": "$2.00",
            "available": true
          },
          {
            "name": "Osem Bamba Peanut Snack | 100g",
            "price": "n/a",
            "available": false
          }
        ]
      },
      {
        "store": "Mirrabooka",
        "timestamp": "2026-05-16T16:54:03.976591+08:00",
        "available": true,
        "products": [
          {
            "name": "Osem Bamba Peanut Snack KB | 25g",
            "price": "$2.00",
            "available": true
          },
          {
            "name": "Osem Bamba Peanut Snack | 100g",
            "price": "n/a",
            "available": false
          }
        ]
      }
    ],
    [
      {
        "store": "Dianella",
        "timestamp": "2026-05-16T18:22:28.075249+08:00",
        "available": true,
        "products": [
          {
            "name": "Osem Bamba Peanut Snack KB | 25g",
            "price": "$2.00",
            "available": true
          },
          {
            "name": "Osem Bamba Peanut Snack | 100g",
            "price": "n/a",
            "available": false
          }
        ]
      },
      {
        "store": "Mirrabooka",
        "timestamp": "2026-05-16T18:22:51.542479+08:00",
        "available": true,
        "products": [
          {
            "name": "Osem Bamba Peanut Snack KB | 25g",
            "price": "$2.00",
            "available": true
          },
          {
            "name": "Osem Bamba Peanut Snack | 100g",
            "price": "n/a",
            "available": false
          }
        ]
      }
    ],
    [
      {
        "store": "Dianella",
        "timestamp": "2026-05-16T19:58:16.242458+08:00",
        "available": true,
        "products": [
          {
            "name": "Osem Bamba Peanut Snack KB | 25g",
            "price": "$2.00",
            "available": true
          },
          {
            "name": "Osem Bamba Peanut Snack | 100g",
            "price": "n/a",
            "available": false
          }
        ]
      },
      {
        "store": "Mirrabooka",
        "timestamp": "2026-05-16T19:58:38.802579+08:00",
        "available": true,
        "products": [
          {
            "name": "Osem Bamba Peanut Snack KB | 25g",
            "price": "$2.00",
            "available": true
          },
          {
            "name": "Osem Bamba Peanut Snack | 100g",
            "price": "n/a",
            "available": false
          }
        ]
      }
    ],
    [
      {
        "store": "Dianella",
        "timestamp": "2026-05-16T21:52:43.477396+08:00",
        "available": true,
        "products": [
          {
            "name": "Osem Bamba Peanut Snack KB | 25g",
            "price": "$2.00",
            "available": true
          },
          {
            "name": "Osem Bamba Peanut Snack | 100g",
            "price": "n/a",
            "available": false
          }
        ]
      },
      {
        "store": "Mirrabooka",
        "timestamp": "2026-05-16T21:53:05.054843+08:00",
        "available": true,
        "products": [
          {
            "name": "Osem Bamba Peanut Snack KB | 25g",
            "price": "$2.00",
            "available": true
          },
          {
            "name": "Osem Bamba Peanut Snack | 100g",
            "price": "n/a",
            "available": false
          }
        ]
      }
    ],
    [
      {
        "store": "Dianella",
        "timestamp": "2026-05-17T07:00:56.929412+08:00",
        "available": true,
        "products": [
          {
            "name": "Osem Bamba Peanut Snack KB | 25g",
            "price": "$2.00",
            "available": true
          },
          {
            "name": "Osem Bamba Peanut Snack | 100g",
            "price": "n/a",
            "available": false
          }
        ]
      },
      {
        "store": "Mirrabooka",
        "timestamp": "2026-05-17T07:01:19.170550+08:00",
        "available": true,
        "products": [
          {
            "name": "Osem Bamba Peanut Snack KB | 25g",
            "price": "$2.00",
            "available": true
          },
          {
            "name": "Osem Bamba Peanut Snack | 100g",
            "price": "n/a",
            "available": false
          }
        ]
      }
    ],
    [
      {
        "store": "Dianella",
        "timestamp": "2026-05-17T12:10:49.139219+08:00",
        "available": true,
        "products": [
          {
            "name": "Osem Bamba Peanut Snack KB | 25g",
            "price": "$2.00",
            "available": true
          },
          {
            "name": "Osem Bamba Peanut Snack | 100g",
            "price": "n/a",
            "available": false
          }
        ]
      },
      {
        "store": "Mirrabooka",
        "timestamp": "2026-05-17T12:11:12.927303+08:00",
        "available": true,
        "products": [
          {
            "name": "Osem Bamba Peanut Snack KB | 25g",
            "price": "$2.00",
            "available": true
          },
          {
            "name": "Osem Bamba Peanut Snack | 100g",
            "price": "n/a",
            "available": false
          }
        ]
      }
    ],
    [
      {
        "store": "Dianella",
        "timestamp": "2026-05-17T15:37:23.627434+08:00",
        "available": true,
        "products": [
          {
            "name": "Osem Bamba Peanut Snack KB | 25g",
            "price": "$2.00",
            "available": true
          },
          {
            "name": "Osem Bamba Peanut Snack | 100g",
            "price": "n/a",
            "available": false
          }
        ]
      },
      {
        "store": "Mirrabooka",
        "timestamp": "2026-05-17T15:37:47.031063+08:00",
        "available": true,
        "products": [
          {
            "name": "Osem Bamba Peanut Snack KB | 25g",
            "price": "$2.00",
            "available": true
          },
          {
            "name": "Osem Bamba Peanut Snack | 100g",
            "price": "n/a",
            "available": false
          }
        ]
      }
    ],
    [
      {
        "store": "Dianella",
        "timestamp": "2026-05-17T17:55:07.783796+08:00",
        "available": true,
        "products": [
          {
            "name": "Osem Bamba Peanut Snack KB | 25g",
            "price": "$2.00",
            "available": true
          },
          {
            "name": "Osem Bamba Peanut Snack | 100g",
            "price": "n/a",
            "available": false
          }
        ]
      },
      {
        "store": "Mirrabooka",
        "timestamp": "2026-05-17T17:55:26.677839+08:00",
        "available": true,
        "products": [
          {
            "name": "Osem Bamba Peanut Snack KB | 25g",
            "price": "$2.00",
            "available": true
          },
          {
            "name": "Osem Bamba Peanut Snack | 100g",
            "price": "n/a",
            "available": false
          }
        ]
      }
    ],
    [
      {
        "store": "Dianella",
        "timestamp": "2026-05-17T19:17:49.881371+08:00",
        "available": true,
        "products": [
          {
            "name": "Osem Bamba Peanut Snack KB | 25g",
            "price": "$2.00",
            "available": true
          },
          {
            "name": "Osem Bamba Peanut Snack | 100g",
            "price": "n/a",
            "available": false
          }
        ]
      },
      {
        "store": "Mirrabooka",
        "timestamp": "2026-05-17T19:18:11.722833+08:00",
        "available": true,
        "products": [
          {
            "name": "Osem Bamba Peanut Snack KB | 25g",
            "price": "$2.00",
            "available": true
          },
          {
            "name": "Osem Bamba Peanut Snack | 100g",
            "price": "n/a",
            "available": false
          }
        ]
      }
    ],
    [
      {
        "store": "Dianella",
        "timestamp": "2026-05-17T21:49:59.855067+08:00",
        "available": true,
        "products": [
          {
            "name": "Osem Bamba Peanut Snack KB | 25g",
            "price": "$2.00",
            "available": true
          },
          {
            "name": "Osem Bamba Peanut Snack | 100g",
            "price": "n/a",
            "available": false
          }
        ]
      },
      {
        "store": "Mirrabooka",
        "timestamp": "2026-05-17T21:50:20.547641+08:00",
        "available": true,
        "products": [
          {
            "name": "Osem Bamba Peanut Snack KB | 25g",
            "price": "$2.00",
            "available": true
          },
          {
            "name": "Osem Bamba Peanut Snack | 100g",
            "price": "n/a",
            "available": false
          }
        ]
      }
    ],
    [
      {
        "store": "Dianella",
        "timestamp": "2026-05-18T07:00:27.765857+08:00",
        "available": true,
        "products": [
          {
            "name": "Osem Bamba Peanut Snack KB | 25g",
            "price": "$2.00",
            "available": true
          },
          {
            "name": "Osem Bamba Peanut Snack | 100g",
            "price": "n/a",
            "available": false
          }
        ]
      },
      {
        "store": "Mirrabooka",
        "timestamp": "2026-05-18T07:00:46.347040+08:00",
        "available": true,
        "products": [
          {
            "name": "Osem Bamba Peanut Snack KB | 25g",
            "price": "$2.00",
            "available": true
          },
          {
            "name": "Osem Bamba Peanut Snack | 100g",
            "price": "n/a",
            "available": false
          }
        ]
      }
    ],
    [
      {
        "store": "Dianella",
        "timestamp": "2026-05-18T08:07:33.324024+08:00",
        "available": true,
        "products": [
          {
            "name": "Osem Bamba Peanut Snack KB | 25g",
            "price": "$2.00",
            "available": true
          },
          {
            "name": "Osem Bamba Peanut Snack | 100g",
            "price": "n/a",
            "available": false
          }
        ]
      },
      {
        "store": "Mirrabooka",
        "timestamp": "2026-05-18T08:07:56.063886+08:00",
        "available": true,
        "products": [
          {
            "name": "Osem Bamba Peanut Snack KB | 25g",
            "price": "$2.00",
            "available": true
          },
          {
            "name": "Osem Bamba Peanut Snack | 100g",
            "price": "n/a",
            "available": false
          }
        ]
      }
    ]
  ]
}